faxir/__init__.py
faxir/api_client.py
faxir/configuration.py
faxir/rest.py
faxir/api/__init__.py
faxir/api/accounts_api.py
faxir/api/archives_api.py
faxir/api/files_api.py
faxir/api/numbers_api.py
faxir/api/outbox_api.py
faxir/models/__init__.py
faxir/models/account.py
faxir/models/account_account_data.py
faxir/models/account_settings.py
faxir/models/account_settings_send_fax.py
faxir/models/account_settings_send_fax_retry.py
faxir/models/error.py
faxir/models/fax.py
faxir/models/fax_cost_details.py
faxir/models/file.py
faxir/models/member_detail.py
faxir/models/number.py
faxir/models/number_notifications.py
faxir/models/outbox.py
faxir/models/outbox_comment.py
faxir/models/outbox_file_changes.py
faxir/models/outbox_files.py
faxir/models/outbox_initiated_from.py
faxir/models/outbox_status_changes.py
faxir/models/payload_fax_modification.py
faxir/models/payload_number_modification.py
faxir/models/payload_outbox.py
faxir/models/payload_outbox_comment.py
faxir/models/payload_outbox_modification.py
faxir/models/payload_outbox_options.py
faxir/models/payload_outbox_options_retry.py
faxir/models/response_account_list.py
faxir/models/response_archive.py
faxir/models/response_archive_data.py
faxir/models/response_number_list.py
faxir/models/response_outbox_list.py
faxir_api-0.2.dist-info/DESCRIPTION.rst
faxir_api-0.2.dist-info/METADATA
faxir_api-0.2.dist-info/RECORD
faxir_api-0.2.dist-info/WHEEL
faxir_api-0.2.dist-info/metadata.json
faxir_api-0.2.dist-info/top_level.txt
sample-app/__init__.py
sample-app/app.py
